etlaas_stream/__init__.py
etlaas_stream/bookmarker/__init__.py
etlaas_stream/bookmarker/bookmarker.py
etlaas_stream/bookmarker/memory_bookmarker.py
etlaas_stream/bookmarker/redis_bookmarker.py
etlaas_stream/infrastructure.py
etlaas_stream/sink.py
etlaas_stream/source.py
etlaas_stream/spec.py
etlaas_stream-20.7.8.dist-info/LICENSE
etlaas_stream-20.7.8.dist-info/WHEEL
etlaas_stream-20.7.8.dist-info/METADATA
etlaas_stream-20.7.8.dist-info/RECORD
