Metadata-Version: 2.1
Name: etlaas-stream
Version: 20.7.8
Summary: Convenience classes for working with data streams.
License: MIT
Author: Andrew Meier
Author-email: ameier38@gmail.com
Requires-Python: >=3.8,<4.0
Classifier: License :: OSI Approved :: MIT License
Classifier: Programming Language :: Python :: 3
Classifier: Programming Language :: Python :: 3.8
Requires-Dist: fastjsonschema (>=2.14.4,<3.0.0)
Requires-Dist: redis (>=3.5.3,<4.0.0)
Requires-Dist: simplejson (>=3.17.0,<4.0.0)
